Metadata-Version: 2.4
Name: chat_exporter
Version: 3.0.1
Summary: A simple Discord chat exporter for Python Discord bots.
Author-email: mahtoid <info@mahto.id>
License: GPL-3.0-only
Project-URL: Homepage, https://github.com/mahtoid/DiscordChatExporterPy
Project-URL: Discord, https://discord.mahto.id/
Project-URL: Donate, https://ko-fi.com/mahtoid
Keywords: chat exporter,discord chat exporter,discord,discordpy,disnake,pycord,nextcord
Classifier: Operating System :: OS Independent
Classifier: Intended Audience :: Developers
Classifier: Natural Language :: English
Classifier: Programming Language :: Python :: 3.6
Classifier: Programming Language :: Python :: 3.7
Classifier: Programming Language :: Python :: 3.8
Classifier: Programming Language :: Python :: 3.9
Classifier: Programming Language :: Python :: 3.10
Classifier: Programming Language :: Python :: 3.11
Classifier: Programming Language :: Python :: 3.12
Classifier: Topic :: Internet
Classifier: Topic :: Software Development :: Libraries
Classifier: Topic :: Software Development :: Libraries :: Python Modules
Classifier: Topic :: Utilities
Classifier: Typing :: Typed
Requires-Python: >=3.6
License-File: LICENSE
Requires-Dist: aiohttp
Requires-Dist: pytz
Requires-Dist: grapheme
Requires-Dist: emoji
Dynamic: license-file
